.DS_Store
examples/__init__.py
examples/playground.py
tests/__init__.py
tests/test_categorical.py
tests/test_distr_heterogeneous.py
tests/test_lik_heterogeneous.py
tests/test_scaler_heterogeneous.py
tests/test_scaler_heterogeneous_object.py
tests/test_scaler_minmax.py
tests/test_scaler_standard.py
tests/test_scalers.py
tests/utils/__init__.py
tests/utils/mock_data.py
torchlikelihoods/.DS_Store
torchlikelihoods/__init__.py
torchlikelihoods/distributions/__init__.py
torchlikelihoods/distributions/delta.py
torchlikelihoods/distributions/heterogeneous.py
torchlikelihoods/likelihoods/__init__.py
torchlikelihoods/likelihoods/base.py
torchlikelihoods/likelihoods/bernoulli.py
torchlikelihoods/likelihoods/beta.py
torchlikelihoods/likelihoods/categorical.py
torchlikelihoods/likelihoods/continous_bernoulli.py
torchlikelihoods/likelihoods/delta.py
torchlikelihoods/likelihoods/heterogeneous.py
torchlikelihoods/likelihoods/normal.py
torchlikelihoods/likelihoods/normal_mean.py
torchlikelihoods/scalers/__init__.py
torchlikelihoods/scalers/base.py
torchlikelihoods/scalers/heterogeneous.py
torchlikelihoods/scalers/heterogeneous_object.py
torchlikelihoods/scalers/identity.py
torchlikelihoods/scalers/min.py
torchlikelihoods/scalers/minmax.py
torchlikelihoods/scalers/scale.py
torchlikelihoods/scalers/scalediff.py
torchlikelihoods/scalers/standard.py
torchlikelihoods/utils/__init__.py
torchlikelihoods/utils/struct.py
torchlikelihoods-0.0.6.4.dist-info/LICENSE
torchlikelihoods-0.0.6.4.dist-info/METADATA
torchlikelihoods-0.0.6.4.dist-info/WHEEL
torchlikelihoods-0.0.6.4.dist-info/top_level.txt
torchlikelihoods-0.0.6.4.dist-info/RECORD
